kiss_ai_stack_client/__init__.py
kiss_ai_stack_client/clients/__init__.py
kiss_ai_stack_client/clients/rest_client.py
kiss_ai_stack_client/clients/ws_client.py
kiss_ai_stack_client/events/__init__.py
kiss_ai_stack_client/events/event_abc.py
kiss_ai_stack_client/events/rest_event.py
kiss_ai_stack_client/events/ws_event.py
kiss_ai_stack_client/utils/__init__.py
kiss_ai_stack_client/utils/logger.py
kiss_ai_stack_client-0.1.0a2.dist-info/LICENSE
kiss_ai_stack_client-0.1.0a2.dist-info/METADATA
kiss_ai_stack_client-0.1.0a2.dist-info/WHEEL
kiss_ai_stack_client-0.1.0a2.dist-info/top_level.txt
kiss_ai_stack_client-0.1.0a2.dist-info/RECORD
